<?xml version="1.0" encoding="utf-8"?><document reference="086.txt"><feature name="detected-plagiarism" source_length="31" source_offset="384" source_reference="1047849.txt" this_length="31" this_offset="8602"/><feature name="detected-plagiarism" source_length="55" source_offset="418" source_reference="1047849.txt" this_length="55" this_offset="8637"/><feature name="detected-plagiarism" source_length="36" source_offset="566" source_reference="1047849.txt" this_length="36" this_offset="8731"/><feature name="detected-plagiarism" source_length="130" source_offset="604" source_reference="1047849.txt" this_length="128" this_offset="8769"/><feature name="detected-plagiarism" source_length="220" source_offset="808" source_reference="1047849.txt" this_length="221" this_offset="8949"/><feature name="detected-plagiarism" source_length="214" source_offset="1030" source_reference="1047849.txt" this_length="215" this_offset="9172"/><feature name="detected-plagiarism" source_length="90" source_offset="1365" source_reference="1047849.txt" this_length="90" this_offset="9516"/><feature name="detected-plagiarism" source_length="32" source_offset="1627" source_reference="1047849.txt" this_length="32" this_offset="9645"/><feature name="detected-plagiarism" source_length="87" source_offset="1664" source_reference="1047849.txt" this_length="90" this_offset="9682"/><feature name="detected-plagiarism" source_length="98" source_offset="2555" source_reference="1047849.txt" this_length="98" this_offset="9806"/><feature name="detected-plagiarism" source_length="103" source_offset="2737" source_reference="1047849.txt" this_length="103" this_offset="9929"/><feature name="detected-plagiarism" source_length="69" source_offset="2899" source_reference="1047849.txt" this_length="69" this_offset="10054"/><feature name="detected-plagiarism" source_length="197" source_offset="3456" source_reference="1047849.txt" this_length="190" this_offset="10158"/><feature name="detected-plagiarism" source_length="37" source_offset="4820" source_reference="1047849.txt" this_length="37" this_offset="10596"/><feature name="detected-plagiarism" source_length="114" source_offset="5013" source_reference="1047849.txt" this_length="112" this_offset="10776"/><feature name="detected-plagiarism" source_length="28" source_offset="5129" source_reference="1047849.txt" this_length="31" this_offset="10890"/><feature name="detected-plagiarism" source_length="63" source_offset="5277" source_reference="1047849.txt" this_length="63" this_offset="10948"/><feature name="detected-plagiarism" source_length="28" source_offset="24103" source_reference="1047849.txt" this_length="31" this_offset="13825"/><feature name="detected-plagiarism" source_length="46" source_offset="31341" source_reference="1047849.txt" this_length="45" this_offset="14614"/><feature name="detected-plagiarism" source_length="27" source_offset="42431" source_reference="1047849.txt" this_length="27" this_offset="14904"/><feature name="detected-plagiarism" source_length="42" source_offset="55125" source_reference="1047849.txt" this_length="42" this_offset="15870"/><feature name="detected-plagiarism" source_length="15" source_offset="45996" source_reference="1047849.txt" this_length="26" this_offset="24862"/></document>