<?xml version="1.0" encoding="utf-8"?><document reference="044.txt"><feature name="detected-plagiarism" source_length="624" source_offset="905" source_reference="5054487.txt" this_length="622" this_offset="48"/><feature name="detected-plagiarism" source_length="270" source_offset="1576" source_reference="5054487.txt" this_length="286" this_offset="692"/><feature name="detected-plagiarism" source_length="234" source_offset="1937" source_reference="5054487.txt" this_length="234" this_offset="1050"/><feature name="detected-plagiarism" source_length="761" source_offset="2185" source_reference="5054487.txt" this_length="797" this_offset="1306"/><feature name="detected-plagiarism" source_length="52" source_offset="3020" source_reference="5054487.txt" this_length="52" this_offset="2219"/><feature name="detected-plagiarism" source_length="257" source_offset="3138" source_reference="5054487.txt" this_length="262" this_offset="2303"/><feature name="detected-plagiarism" source_length="72" source_offset="3421" source_reference="5054487.txt" this_length="82" this_offset="2612"/><feature name="detected-plagiarism" source_length="284" source_offset="3556" source_reference="5054487.txt" this_length="290" this_offset="2789"/><feature name="detected-plagiarism" source_length="306" source_offset="3853" source_reference="5054487.txt" this_length="307" this_offset="3155"/><feature name="detected-plagiarism" source_length="62" source_offset="4185" source_reference="5054487.txt" this_length="62" this_offset="3465"/><feature name="detected-plagiarism" source_length="881" source_offset="4288" source_reference="5054487.txt" this_length="916" this_offset="3531"/><feature name="detected-plagiarism" source_length="63" source_offset="5592" source_reference="5054487.txt" this_length="71" this_offset="4487"/><feature name="detected-plagiarism" source_length="109" source_offset="5749" source_reference="5054487.txt" this_length="123" this_offset="4643"/><feature name="detected-plagiarism" source_length="113" source_offset="5864" source_reference="5054487.txt" this_length="113" this_offset="4805"/><feature name="detected-plagiarism" source_length="47" source_offset="6024" source_reference="5054487.txt" this_length="47" this_offset="4954"/><feature name="detected-plagiarism" source_length="623" source_offset="6091" source_reference="5054487.txt" this_length="634" this_offset="5036"/><feature name="detected-plagiarism" source_length="59" source_offset="7124" source_reference="5054487.txt" this_length="59" this_offset="5883"/><feature name="detected-plagiarism" source_length="40" source_offset="7235" source_reference="5054487.txt" this_length="36" this_offset="5997"/><feature name="detected-plagiarism" source_length="81" source_offset="7371" source_reference="5054487.txt" this_length="81" this_offset="6083"/><feature name="detected-plagiarism" source_length="42" source_offset="7504" source_reference="5054487.txt" this_length="42" this_offset="6180"/><feature name="detected-plagiarism" source_length="107" source_offset="7807" source_reference="5054487.txt" this_length="107" this_offset="6340"/><feature name="detected-plagiarism" source_length="153" source_offset="7651" source_reference="5054487.txt" this_length="164" this_offset="6457"/><feature name="detected-plagiarism" source_length="40" source_offset="7919" source_reference="5054487.txt" this_length="40" this_offset="6624"/><feature name="detected-plagiarism" source_length="50" source_offset="7996" source_reference="5054487.txt" this_length="50" this_offset="6713"/><feature name="detected-plagiarism" source_length="123" source_offset="8083" source_reference="5054487.txt" this_length="137" this_offset="6785"/><feature name="detected-plagiarism" source_length="339" source_offset="8304" source_reference="5054487.txt" this_length="333" this_offset="6984"/><feature name="detected-plagiarism" source_length="327" source_offset="8645" source_reference="5054487.txt" this_length="305" this_offset="7334"/><feature name="detected-plagiarism" source_length="32" source_offset="8993" source_reference="5054487.txt" this_length="30" this_offset="7667"/><feature name="detected-plagiarism" source_length="181" source_offset="9063" source_reference="5054487.txt" this_length="193" this_offset="7715"/><feature name="detected-plagiarism" source_length="511" source_offset="9258" source_reference="5054487.txt" this_length="506" this_offset="7910"/><feature name="detected-plagiarism" source_length="182" source_offset="9796" source_reference="5054487.txt" this_length="182" this_offset="8463"/><feature name="detected-plagiarism" source_length="971" source_offset="10000" source_reference="5054487.txt" this_length="989" this_offset="8672"/><feature name="detected-plagiarism" source_length="185" source_offset="10998" source_reference="5054487.txt" this_length="187" this_offset="9683"/><feature name="detected-plagiarism" source_length="370" source_offset="11186" source_reference="5054487.txt" this_length="361" this_offset="9881"/><feature name="detected-plagiarism" source_length="125" source_offset="11587" source_reference="5054487.txt" this_length="116" this_offset="10256"/><feature name="detected-plagiarism" source_length="67" source_offset="11727" source_reference="5054487.txt" this_length="75" this_offset="10395"/><feature name="detected-plagiarism" source_length="117" source_offset="11996" source_reference="5054487.txt" this_length="129" this_offset="10474"/><feature name="detected-plagiarism" source_length="84" source_offset="12147" source_reference="5054487.txt" this_length="82" this_offset="10681"/><feature name="detected-plagiarism" source_length="207" source_offset="12281" source_reference="5054487.txt" this_length="218" this_offset="10788"/><feature name="detected-plagiarism" source_length="188" source_offset="12529" source_reference="5054487.txt" this_length="182" this_offset="11041"/><feature name="detected-plagiarism" source_length="63" source_offset="12726" source_reference="5054487.txt" this_length="63" this_offset="11232"/><feature name="detected-plagiarism" source_length="136" source_offset="12800" source_reference="5054487.txt" this_length="146" this_offset="11306"/><feature name="detected-plagiarism" source_length="53" source_offset="13140" source_reference="5054487.txt" this_length="63" this_offset="11665"/><feature name="detected-plagiarism" source_length="88" source_offset="13292" source_reference="5054487.txt" this_length="90" this_offset="11733"/><feature name="detected-plagiarism" source_length="45" source_offset="13435" source_reference="5054487.txt" this_length="43" this_offset="11905"/><feature name="detected-plagiarism" source_length="22" source_offset="9376" source_reference="5054487.txt" this_length="22" this_offset="18466"/></document>