<?xml version="1.0" encoding="utf-8"?><document reference="106.txt"><feature name="detected-plagiarism" source_length="96" source_offset="3225" source_reference="4707087.txt" this_length="96" this_offset="7760"/><feature name="detected-plagiarism" source_length="116" source_offset="3362" source_reference="4707087.txt" this_length="109" this_offset="7873"/><feature name="detected-plagiarism" source_length="81" source_offset="3502" source_reference="4707087.txt" this_length="81" this_offset="7984"/><feature name="detected-plagiarism" source_length="43" source_offset="3608" source_reference="4707087.txt" this_length="43" this_offset="8077"/><feature name="detected-plagiarism" source_length="83" source_offset="3775" source_reference="4707087.txt" this_length="79" this_offset="8129"/><feature name="detected-plagiarism" source_length="79" source_offset="3922" source_reference="4707087.txt" this_length="79" this_offset="8237"/><feature name="detected-plagiarism" source_length="138" source_offset="4046" source_reference="4707087.txt" this_length="122" this_offset="8341"/><feature name="detected-plagiarism" source_length="82" source_offset="4214" source_reference="4707087.txt" this_length="82" this_offset="8466"/><feature name="detected-plagiarism" source_length="138" source_offset="4344" source_reference="4707087.txt" this_length="125" this_offset="8564"/><feature name="detected-plagiarism" source_length="114" source_offset="4862" source_reference="4707087.txt" this_length="114" this_offset="8867"/><feature name="detected-plagiarism" source_length="45" source_offset="5117" source_reference="4707087.txt" this_length="45" this_offset="9120"/><feature name="detected-plagiarism" source_length="220" source_offset="5813" source_reference="4707087.txt" this_length="215" this_offset="9459"/><feature name="detected-plagiarism" source_length="110" source_offset="6607" source_reference="4707087.txt" this_length="102" this_offset="9766"/><feature name="detected-plagiarism" source_length="1070" source_offset="7188" source_reference="4707087.txt" this_length="1119" this_offset="9925"/></document>