<?xml version="1.0" ?>
<document reference="041.txt">
	<feature name="plagiarism" obfuscation="HPR" source_language="ru" source_length="68" source_offset="298" source_reference="4547532.txt" this_language="ru" this_length="59" this_offset="16038" txt_extraction_err="0" type="manual"/>
	<feature name="plagiarism" obfuscation="LPR" source_language="ru" source_length="127" source_offset="367" source_reference="4547532.txt" this_language="ru" this_length="103" this_offset="16098" txt_extraction_err="0" type="manual"/>
	<feature name="plagiarism" obfuscation="ADD" source_language="ru" source_length="146" source_offset="495" source_reference="4547532.txt" this_language="ru" this_length="160" this_offset="16363" txt_extraction_err="0" type="manual"/>
	<feature name="plagiarism" obfuscation="HPR" source_language="ru" source_length="121" source_offset="642" source_reference="4547532.txt" this_language="ru" this_length="108" this_offset="16574" txt_extraction_err="0" type="manual"/>
	<feature name="plagiarism" obfuscation="HPR" source_language="ru" source_length="103" source_offset="764" source_reference="4547532.txt" this_language="ru" this_length="106" this_offset="16683" txt_extraction_err="0" type="manual"/>
	<feature name="plagiarism" obfuscation="HPR" source_language="ru" source_length="175" source_offset="868" source_reference="4547532.txt" this_language="ru" this_length="137" this_offset="16860" txt_extraction_err="0" type="manual"/>
	<feature name="plagiarism" obfuscation="LPR" source_language="ru" source_length="146" source_offset="1044" source_reference="4547532.txt" this_language="ru" this_length="131" this_offset="16998" txt_extraction_err="0" type="manual"/>
	<feature name="plagiarism" obfuscation="HPR" source_language="ru" source_length="108" source_offset="1191" source_reference="4547532.txt" this_language="ru" this_length="105" this_offset="17130" txt_extraction_err="0" type="manual"/>
	<feature name="plagiarism" obfuscation="SSP" source_language="ru" source_length="305" source_offset="1300" source_reference="4547532.txt" this_language="ru" this_length="305" this_offset="17236" txt_extraction_err="0" type="manual"/>
	<feature name="plagiarism" obfuscation="SSP" source_language="ru" source_length="305" source_offset="1300" source_reference="4547532.txt" this_language="ru" this_length="120" this_offset="17542" txt_extraction_err="0" type="manual"/>
	<feature name="plagiarism" obfuscation="SSP" source_language="ru" source_length="211" source_offset="1608" source_reference="4547532.txt" this_language="ru" this_length="126" this_offset="17663" txt_extraction_err="0" type="manual"/>
	<feature name="plagiarism" obfuscation="SSP" source_language="ru" source_length="211" source_offset="1608" source_reference="4547532.txt" this_language="ru" this_length="84" this_offset="17790" txt_extraction_err="0" type="manual"/>
	<feature name="plagiarism" obfuscation="HPR" source_language="ru" source_length="103" source_offset="1820" source_reference="4547532.txt" this_language="ru" this_length="60" this_offset="17875" txt_extraction_err="0" type="manual"/>
	<feature name="plagiarism" obfuscation="DEL" source_language="ru" source_length="142" source_offset="1924" source_reference="4547532.txt" this_language="ru" this_length="86" this_offset="17936" txt_extraction_err="0" type="manual"/>
	<feature name="plagiarism" obfuscation="SSP" source_language="ru" source_length="267" source_offset="2067" source_reference="4547532.txt" this_language="ru" this_length="181" this_offset="18023" txt_extraction_err="0" type="manual"/>
	<feature name="plagiarism" obfuscation="SSP" source_language="ru" source_length="267" source_offset="2067" source_reference="4547532.txt" this_language="ru" this_length="86" this_offset="18205" txt_extraction_err="0" type="manual"/>
	<feature name="plagiarism" obfuscation="LPR" source_language="ru" source_length="283" source_offset="2337" source_reference="4547532.txt" this_language="ru" this_length="290" this_offset="18292" txt_extraction_err="0" type="manual"/>
	<feature name="plagiarism" obfuscation="CCT" source_language="ru" source_length="159" source_offset="2621" source_reference="4547532.txt" this_language="ru" this_length="358" this_offset="18583" txt_extraction_err="0" type="manual"/>
	<feature name="plagiarism" obfuscation="CCT" source_language="ru" source_length="198" source_offset="2781" source_reference="4547532.txt" this_language="ru" this_length="358" this_offset="18583" txt_extraction_err="0" type="manual"/>
	<feature name="plagiarism" obfuscation="CCT" source_language="ru" source_length="226" source_offset="2980" source_reference="4547532.txt" this_language="ru" this_length="355" this_offset="18942" txt_extraction_err="0" type="manual"/>
	<feature name="plagiarism" obfuscation="CCT" source_language="ru" source_length="129" source_offset="3207" source_reference="4547532.txt" this_language="ru" this_length="355" this_offset="18942" txt_extraction_err="0" type="manual"/>
	<feature name="plagiarism" obfuscation="LPR" source_language="ru" source_length="274" source_offset="3337" source_reference="4547532.txt" this_language="ru" this_length="279" this_offset="19298" txt_extraction_err="0" type="manual"/>
	<feature name="plagiarism" obfuscation="LPR" source_language="ru" source_length="99" source_offset="3614" source_reference="4547532.txt" this_language="ru" this_length="95" this_offset="19578" txt_extraction_err="0" type="manual"/>
	<feature name="plagiarism" obfuscation="HPR" source_language="ru" source_length="107" source_offset="3714" source_reference="4547532.txt" this_language="ru" this_length="84" this_offset="19674" txt_extraction_err="0" type="manual"/>
	<feature name="plagiarism" obfuscation="HPR" source_language="ru" source_length="54" source_offset="3822" source_reference="4547532.txt" this_language="ru" this_length="59" this_offset="19759" txt_extraction_err="0" type="manual"/>
	<feature name="plagiarism" obfuscation="LPR" source_language="ru" source_length="280" source_offset="3877" source_reference="4547532.txt" this_language="ru" this_length="291" this_offset="19819" txt_extraction_err="0" type="manual"/>
	<feature name="plagiarism" obfuscation="DEL" source_language="ru" source_length="147" source_offset="4158" source_reference="4547532.txt" this_language="ru" this_length="73" this_offset="20111" txt_extraction_err="0" type="manual"/>
	<feature name="plagiarism" obfuscation="DEL" source_language="ru" source_length="196" source_offset="4306" source_reference="4547532.txt" this_language="ru" this_length="159" this_offset="20185" txt_extraction_err="0" type="manual"/>
</document>
