<?xml version="1.0" encoding="utf-8"?><document reference="016.txt"><feature name="detected-plagiarism" source_length="74" source_offset="390" source_reference="2505896.txt" this_length="74" this_offset="2304"/><feature name="detected-plagiarism" source_length="58" source_offset="492" source_reference="2505896.txt" this_length="58" this_offset="6122"/><feature name="detected-plagiarism" source_length="55" source_offset="699" source_reference="2505896.txt" this_length="55" this_offset="6243"/><feature name="detected-plagiarism" source_length="58" source_offset="833" source_reference="2505896.txt" this_length="58" this_offset="6317"/><feature name="detected-plagiarism" source_length="105" source_offset="1359" source_reference="2505896.txt" this_length="106" this_offset="6503"/><feature name="detected-plagiarism" source_length="76" source_offset="1548" source_reference="2505896.txt" this_length="73" this_offset="6652"/><feature name="detected-plagiarism" source_length="58" source_offset="1624" source_reference="2505896.txt" this_length="58" this_offset="6732"/><feature name="detected-plagiarism" source_length="92" source_offset="1783" source_reference="2505896.txt" this_length="92" this_offset="6861"/><feature name="detected-plagiarism" source_length="119" source_offset="1984" source_reference="2505896.txt" this_length="111" this_offset="7076"/><feature name="detected-plagiarism" source_length="55" source_offset="3462" source_reference="2505896.txt" this_length="55" this_offset="7281"/><feature name="detected-plagiarism" source_length="108" source_offset="3524" source_reference="2505896.txt" this_length="100" this_offset="7364"/><feature name="detected-plagiarism" source_length="55" source_offset="4311" source_reference="2505896.txt" this_length="55" this_offset="7548"/><feature name="detected-plagiarism" source_length="152" source_offset="4372" source_reference="2505896.txt" this_length="144" this_offset="7641"/><feature name="detected-plagiarism" source_length="58" source_offset="4941" source_reference="2505896.txt" this_length="58" this_offset="7880"/><feature name="detected-plagiarism" source_length="109" source_offset="4999" source_reference="2505896.txt" this_length="109" this_offset="7938"/><feature name="detected-plagiarism" source_length="62" source_offset="5332" source_reference="2505896.txt" this_length="62" this_offset="8292"/><feature name="detected-plagiarism" source_length="78" source_offset="5434" source_reference="2505896.txt" this_length="70" this_offset="8375"/><feature name="detected-plagiarism" source_length="55" source_offset="6223" source_reference="2505896.txt" this_length="55" this_offset="8460"/><feature name="detected-plagiarism" source_length="103" source_offset="6278" source_reference="2505896.txt" this_length="95" this_offset="8515"/><feature name="detected-plagiarism" source_length="88" source_offset="6814" source_reference="2505896.txt" this_length="80" this_offset="8842"/><feature name="detected-plagiarism" source_length="54" source_offset="7066" source_reference="2505896.txt" this_length="54" this_offset="8939"/></document>