<?xml version="1.0" encoding="utf-8"?><document reference="030.txt"><feature name="detected-plagiarism" source_length="46" source_offset="119" source_reference="1195455.txt" this_length="36" this_offset="12301"/><feature name="detected-plagiarism" source_length="44" source_offset="491" source_reference="1195455.txt" this_length="36" this_offset="12301"/><feature name="detected-plagiarism" source_length="46" source_offset="119" source_reference="1195455.txt" this_length="38" this_offset="12305"/><feature name="detected-plagiarism" source_length="44" source_offset="491" source_reference="1195455.txt" this_length="38" this_offset="12305"/><feature name="detected-plagiarism" source_length="43" source_offset="254" source_reference="1195455.txt" this_length="58" this_offset="12704"/><feature name="detected-plagiarism" source_length="43" source_offset="361" source_reference="1195455.txt" this_length="58" this_offset="12704"/><feature name="detected-plagiarism" source_length="48" source_offset="5005" source_reference="1195455.txt" this_length="47" this_offset="12856"/><feature name="detected-plagiarism" source_length="105" source_offset="8304" source_reference="1195455.txt" this_length="85" this_offset="16699"/><feature name="detected-plagiarism" source_length="76" source_offset="8412" source_reference="1195455.txt" this_length="76" this_offset="16839"/><feature name="detected-plagiarism" source_length="182" source_offset="8568" source_reference="1195455.txt" this_length="178" this_offset="16907"/></document>