<?xml version="1.0" encoding="utf-8"?><document reference="041.txt"><feature name="detected-plagiarism" source_length="61" source_offset="345" source_reference="1521663.txt" this_length="61" this_offset="8150"/><feature name="detected-plagiarism" source_length="87" source_offset="1061" source_reference="1521663.txt" this_length="85" this_offset="8872"/><feature name="detected-plagiarism" source_length="68" source_offset="1246" source_reference="1521663.txt" this_length="72" this_offset="9051"/><feature name="detected-plagiarism" source_length="66" source_offset="1340" source_reference="1521663.txt" this_length="59" this_offset="9148"/><feature name="detected-plagiarism" source_length="91" source_offset="1355" source_reference="1521663.txt" this_length="79" this_offset="9168"/><feature name="detected-plagiarism" source_length="154" source_offset="1378" source_reference="1521663.txt" this_length="139" this_offset="9201"/><feature name="detected-plagiarism" source_length="156" source_offset="1538" source_reference="1521663.txt" this_length="156" this_offset="9432"/><feature name="detected-plagiarism" source_length="72" source_offset="1883" source_reference="1521663.txt" this_length="71" this_offset="9829"/><feature name="detected-plagiarism" source_length="126" source_offset="1990" source_reference="1521663.txt" this_length="126" this_offset="9940"/><feature name="detected-plagiarism" source_length="157" source_offset="2241" source_reference="1521663.txt" this_length="157" this_offset="10189"/><feature name="detected-plagiarism" source_length="123" source_offset="2420" source_reference="1521663.txt" this_length="106" this_offset="10348"/><feature name="detected-plagiarism" source_length="171" source_offset="2674" source_reference="1521663.txt" this_length="173" this_offset="10636"/><feature name="detected-plagiarism" source_length="1012" source_offset="2849" source_reference="1521663.txt" this_length="990" this_offset="10817"/><feature name="detected-plagiarism" source_length="59" source_offset="3863" source_reference="1521663.txt" this_length="59" this_offset="11822"/></document>