<?xml version="1.0" encoding="utf-8"?><document reference="068.txt"><feature name="detected-plagiarism" source_length="62" source_offset="31443" source_reference="2176270.txt" this_length="50" this_offset="221"/><feature name="detected-plagiarism" source_length="59" source_offset="30647" source_reference="2176270.txt" this_length="47" this_offset="9049"/><feature name="detected-plagiarism" source_length="122" source_offset="33018" source_reference="2176270.txt" this_length="47" this_offset="9049"/><feature name="detected-plagiarism" source_length="67" source_offset="33576" source_reference="2176270.txt" this_length="47" this_offset="9049"/><feature name="detected-plagiarism" source_length="50" source_offset="34333" source_reference="2176270.txt" this_length="47" this_offset="9049"/><feature name="detected-plagiarism" source_length="82" source_offset="35824" source_reference="2176270.txt" this_length="47" this_offset="9049"/><feature name="detected-plagiarism" source_length="43" source_offset="36311" source_reference="2176270.txt" this_length="47" this_offset="9049"/><feature name="detected-plagiarism" source_length="54" source_offset="36438" source_reference="2176270.txt" this_length="47" this_offset="9049"/><feature name="detected-plagiarism" source_length="49" source_offset="37376" source_reference="2176270.txt" this_length="47" this_offset="9049"/><feature name="detected-plagiarism" source_length="63" source_offset="38458" source_reference="2176270.txt" this_length="47" this_offset="9049"/><feature name="detected-plagiarism" source_length="66" source_offset="38831" source_reference="2176270.txt" this_length="47" this_offset="9049"/><feature name="detected-plagiarism" source_length="66" source_offset="39233" source_reference="2176270.txt" this_length="47" this_offset="9049"/><feature name="detected-plagiarism" source_length="61" source_offset="40243" source_reference="2176270.txt" this_length="47" this_offset="9049"/><feature name="detected-plagiarism" source_length="55" source_offset="44390" source_reference="2176270.txt" this_length="47" this_offset="9049"/><feature name="detected-plagiarism" source_length="230" source_offset="44500" source_reference="2176270.txt" this_length="47" this_offset="9049"/><feature name="detected-plagiarism" source_length="100" source_offset="44743" source_reference="2176270.txt" this_length="47" this_offset="9049"/><feature name="detected-plagiarism" source_length="104" source_offset="44850" source_reference="2176270.txt" this_length="47" this_offset="9049"/><feature name="detected-plagiarism" source_length="161" source_offset="44981" source_reference="2176270.txt" this_length="47" this_offset="9049"/><feature name="detected-plagiarism" source_length="90" source_offset="45182" source_reference="2176270.txt" this_length="47" this_offset="9049"/><feature name="detected-plagiarism" source_length="43" source_offset="45283" source_reference="2176270.txt" this_length="47" this_offset="9049"/><feature name="detected-plagiarism" source_length="79" source_offset="45374" source_reference="2176270.txt" this_length="47" this_offset="9049"/><feature name="detected-plagiarism" source_length="59" source_offset="30647" source_reference="2176270.txt" this_length="69" this_offset="9055"/><feature name="detected-plagiarism" source_length="122" source_offset="33018" source_reference="2176270.txt" this_length="69" this_offset="9055"/><feature name="detected-plagiarism" source_length="67" source_offset="33576" source_reference="2176270.txt" this_length="69" this_offset="9055"/><feature name="detected-plagiarism" source_length="50" source_offset="34333" source_reference="2176270.txt" this_length="69" this_offset="9055"/><feature name="detected-plagiarism" source_length="82" source_offset="35824" source_reference="2176270.txt" this_length="69" this_offset="9055"/><feature name="detected-plagiarism" source_length="43" source_offset="36311" source_reference="2176270.txt" this_length="69" this_offset="9055"/><feature name="detected-plagiarism" source_length="54" source_offset="36438" source_reference="2176270.txt" this_length="69" this_offset="9055"/><feature name="detected-plagiarism" source_length="49" source_offset="37376" source_reference="2176270.txt" this_length="69" this_offset="9055"/><feature name="detected-plagiarism" source_length="63" source_offset="38458" source_reference="2176270.txt" this_length="69" this_offset="9055"/><feature name="detected-plagiarism" source_length="66" source_offset="38831" source_reference="2176270.txt" this_length="69" this_offset="9055"/><feature name="detected-plagiarism" source_length="66" source_offset="39233" source_reference="2176270.txt" this_length="69" this_offset="9055"/><feature name="detected-plagiarism" source_length="61" source_offset="40243" source_reference="2176270.txt" this_length="69" this_offset="9055"/><feature name="detected-plagiarism" source_length="55" source_offset="44390" source_reference="2176270.txt" this_length="69" this_offset="9055"/><feature name="detected-plagiarism" source_length="230" source_offset="44500" source_reference="2176270.txt" this_length="69" this_offset="9055"/><feature name="detected-plagiarism" source_length="100" source_offset="44743" source_reference="2176270.txt" this_length="69" this_offset="9055"/><feature name="detected-plagiarism" source_length="104" source_offset="44850" source_reference="2176270.txt" this_length="69" this_offset="9055"/><feature name="detected-plagiarism" source_length="161" source_offset="44981" source_reference="2176270.txt" this_length="69" this_offset="9055"/><feature name="detected-plagiarism" source_length="90" source_offset="45182" source_reference="2176270.txt" this_length="69" this_offset="9055"/><feature name="detected-plagiarism" source_length="43" source_offset="45283" source_reference="2176270.txt" this_length="69" this_offset="9055"/><feature name="detected-plagiarism" source_length="79" source_offset="45374" source_reference="2176270.txt" this_length="69" this_offset="9055"/><feature name="detected-plagiarism" source_length="59" source_offset="30647" source_reference="2176270.txt" this_length="67" this_offset="9064"/><feature name="detected-plagiarism" source_length="122" source_offset="33018" source_reference="2176270.txt" this_length="67" this_offset="9064"/><feature name="detected-plagiarism" source_length="67" source_offset="33576" source_reference="2176270.txt" this_length="67" this_offset="9064"/><feature name="detected-plagiarism" source_length="50" source_offset="34333" source_reference="2176270.txt" this_length="67" this_offset="9064"/><feature name="detected-plagiarism" source_length="82" source_offset="35824" source_reference="2176270.txt" this_length="67" this_offset="9064"/><feature name="detected-plagiarism" source_length="43" source_offset="36311" source_reference="2176270.txt" this_length="67" this_offset="9064"/><feature name="detected-plagiarism" source_length="54" source_offset="36438" source_reference="2176270.txt" this_length="67" this_offset="9064"/><feature name="detected-plagiarism" source_length="49" source_offset="37376" source_reference="2176270.txt" this_length="67" this_offset="9064"/><feature name="detected-plagiarism" source_length="63" source_offset="38458" source_reference="2176270.txt" this_length="67" this_offset="9064"/><feature name="detected-plagiarism" source_length="66" source_offset="38831" source_reference="2176270.txt" this_length="67" this_offset="9064"/><feature name="detected-plagiarism" source_length="66" source_offset="39233" source_reference="2176270.txt" this_length="67" this_offset="9064"/><feature name="detected-plagiarism" source_length="61" source_offset="40243" source_reference="2176270.txt" this_length="67" this_offset="9064"/><feature name="detected-plagiarism" source_length="55" source_offset="44390" source_reference="2176270.txt" this_length="67" this_offset="9064"/><feature name="detected-plagiarism" source_length="230" source_offset="44500" source_reference="2176270.txt" this_length="67" this_offset="9064"/><feature name="detected-plagiarism" source_length="100" source_offset="44743" source_reference="2176270.txt" this_length="67" this_offset="9064"/><feature name="detected-plagiarism" source_length="104" source_offset="44850" source_reference="2176270.txt" this_length="67" this_offset="9064"/><feature name="detected-plagiarism" source_length="161" source_offset="44981" source_reference="2176270.txt" this_length="67" this_offset="9064"/><feature name="detected-plagiarism" source_length="90" source_offset="45182" source_reference="2176270.txt" this_length="67" this_offset="9064"/><feature name="detected-plagiarism" source_length="43" source_offset="45283" source_reference="2176270.txt" this_length="67" this_offset="9064"/><feature name="detected-plagiarism" source_length="79" source_offset="45374" source_reference="2176270.txt" this_length="67" this_offset="9064"/><feature name="detected-plagiarism" source_length="59" source_offset="30647" source_reference="2176270.txt" this_length="66" this_offset="9077"/><feature name="detected-plagiarism" source_length="122" source_offset="33018" source_reference="2176270.txt" this_length="66" this_offset="9077"/><feature name="detected-plagiarism" source_length="67" source_offset="33576" source_reference="2176270.txt" this_length="66" this_offset="9077"/><feature name="detected-plagiarism" source_length="50" source_offset="34333" source_reference="2176270.txt" this_length="66" this_offset="9077"/><feature name="detected-plagiarism" source_length="82" source_offset="35824" source_reference="2176270.txt" this_length="66" this_offset="9077"/><feature name="detected-plagiarism" source_length="43" source_offset="36311" source_reference="2176270.txt" this_length="66" this_offset="9077"/><feature name="detected-plagiarism" source_length="54" source_offset="36438" source_reference="2176270.txt" this_length="66" this_offset="9077"/><feature name="detected-plagiarism" source_length="49" source_offset="37376" source_reference="2176270.txt" this_length="66" this_offset="9077"/><feature name="detected-plagiarism" source_length="63" source_offset="38458" source_reference="2176270.txt" this_length="66" this_offset="9077"/><feature name="detected-plagiarism" source_length="66" source_offset="38831" source_reference="2176270.txt" this_length="66" this_offset="9077"/><feature name="detected-plagiarism" source_length="66" source_offset="39233" source_reference="2176270.txt" this_length="66" this_offset="9077"/><feature name="detected-plagiarism" source_length="61" source_offset="40243" source_reference="2176270.txt" this_length="66" this_offset="9077"/><feature name="detected-plagiarism" source_length="55" source_offset="44390" source_reference="2176270.txt" this_length="66" this_offset="9077"/><feature name="detected-plagiarism" source_length="230" source_offset="44500" source_reference="2176270.txt" this_length="66" this_offset="9077"/><feature name="detected-plagiarism" source_length="100" source_offset="44743" source_reference="2176270.txt" this_length="66" this_offset="9077"/><feature name="detected-plagiarism" source_length="104" source_offset="44850" source_reference="2176270.txt" this_length="66" this_offset="9077"/><feature name="detected-plagiarism" source_length="161" source_offset="44981" source_reference="2176270.txt" this_length="66" this_offset="9077"/><feature name="detected-plagiarism" source_length="90" source_offset="45182" source_reference="2176270.txt" this_length="66" this_offset="9077"/><feature name="detected-plagiarism" source_length="43" source_offset="45283" source_reference="2176270.txt" this_length="66" this_offset="9077"/><feature name="detected-plagiarism" source_length="79" source_offset="45374" source_reference="2176270.txt" this_length="66" this_offset="9077"/><feature name="detected-plagiarism" source_length="74" source_offset="1545" source_reference="2176270.txt" this_length="74" this_offset="11843"/><feature name="detected-plagiarism" source_length="81" source_offset="7987" source_reference="2176270.txt" this_length="81" this_offset="11980"/><feature name="detected-plagiarism" source_length="75" source_offset="9034" source_reference="2176270.txt" this_length="75" this_offset="12178"/><feature name="detected-plagiarism" source_length="74" source_offset="1769" source_reference="2176270.txt" this_length="74" this_offset="15516"/></document>