<?xml version="1.0" encoding="utf-8"?><document reference="2020.txt"><feature name="detected-plagiarism" source_length="35" source_offset="615" source_reference="3345539.txt" this_length="23" this_offset="2833"/><feature name="detected-plagiarism" source_length="32" source_offset="1815" source_reference="3345539.txt" this_length="23" this_offset="2833"/><feature name="detected-plagiarism" source_length="31" source_offset="726" source_reference="3345539.txt" this_length="25" this_offset="3618"/><feature name="detected-plagiarism" source_length="34" source_offset="2175" source_reference="3345539.txt" this_length="34" this_offset="4661"/><feature name="detected-plagiarism" source_length="55" source_offset="10414" source_reference="3345539.txt" this_length="53" this_offset="9430"/><feature name="detected-plagiarism" source_length="37" source_offset="11568" source_reference="3345539.txt" this_length="52" this_offset="9670"/><feature name="detected-plagiarism" source_length="41" source_offset="11510" source_reference="3345539.txt" this_length="46" this_offset="9870"/><feature name="detected-plagiarism" source_length="52" source_offset="9661" source_reference="3345539.txt" this_length="35" this_offset="10480"/><feature name="detected-plagiarism" source_length="39" source_offset="3055" source_reference="3345539.txt" this_length="28" this_offset="12425"/></document>