<?xml version="1.0" encoding="utf-8"?><document reference="2035.txt"><feature name="detected-plagiarism" source_length="29" source_offset="203" source_reference="1063916.txt" this_length="29" this_offset="17"/><feature name="detected-plagiarism" source_length="39" source_offset="2191" source_reference="1063916.txt" this_length="37" this_offset="7521"/><feature name="detected-plagiarism" source_length="135" source_offset="2301" source_reference="1063916.txt" this_length="131" this_offset="7674"/><feature name="detected-plagiarism" source_length="46" source_offset="2559" source_reference="1063916.txt" this_length="49" this_offset="7921"/><feature name="detected-plagiarism" source_length="35" source_offset="2679" source_reference="1063916.txt" this_length="38" this_offset="8044"/><feature name="detected-plagiarism" source_length="33" source_offset="2742" source_reference="1063916.txt" this_length="34" this_offset="8133"/><feature name="detected-plagiarism" source_length="23" source_offset="2966" source_reference="1063916.txt" this_length="23" this_offset="8335"/><feature name="detected-plagiarism" source_length="53" source_offset="3088" source_reference="1063916.txt" this_length="54" this_offset="8440"/><feature name="detected-plagiarism" source_length="26" source_offset="4807" source_reference="1063916.txt" this_length="26" this_offset="10160"/><feature name="detected-plagiarism" source_length="63" source_offset="5139" source_reference="1063916.txt" this_length="63" this_offset="10349"/><feature name="detected-plagiarism" source_length="69" source_offset="6223" source_reference="1063916.txt" this_length="69" this_offset="1706"/><feature name="detected-plagiarism" source_length="73" source_offset="6361" source_reference="1063916.txt" this_length="74" this_offset="1914"/><feature name="detected-plagiarism" source_length="61" source_offset="6600" source_reference="1063916.txt" this_length="58" this_offset="2195"/><feature name="detected-plagiarism" source_length="21" source_offset="7330" source_reference="1063916.txt" this_length="21" this_offset="4298"/><feature name="detected-plagiarism" source_length="5" source_offset="7611" source_reference="1063916.txt" this_length="9" this_offset="5396"/></document>